{
  "schemaVersion": 1,
  "registryId": "gamecastle.wp2.mechanic-registry",
  "owner": "ProductMechanicRegistry",
  "status": "designed",
  "closedEnumeration": false,
  "purpose": "Provide stable product-mechanic capability IDs between creative semantics and low-level GDJS capabilities without defining a second meaning dictionary.",
  "truthBoundary": {
    "meaningOwner": "ai/semantic-mapping/semantic-feedback.json",
    "runtimeCapabilityOwner": "ai/gdevelop-truth/capability-universe.json",
    "semanticRoutingProjection": "ai/semantic-mapping/capability-semantic-index.json",
    "mechanicContractOwner": "this registry",
    "rule": "semanticRefs define why a mechanic exists; capability selectors define how approved implementations may be evidenced; neither side may copy the other owner's definitions."
  },
  "discoveryReferenceFormat": "mechanic-registry#/mechanics/<mechanic-id>",
  "executableReferenceFormat": "mechanic-registry#/approvedRevisions/<mechanic-id>/<revision>/<content-hash>",
  "revisionPolicy": {
    "mechanicsMapIsDiscoveryProjection": true,
    "discoveryEntriesAreNotExecutable": true,
    "approvedRevisionRecordsAreAppendOnly": true,
    "approvedReferencePins": ["mechanicId", "revision", "contentHash"],
    "currentAliasForbiddenInBuildArtifacts": true,
    "newRevisionNeverMutatesPriorRecord": true
  },
  "entryRequired": ["id", "revision", "status", "category", "semanticRefs", "provides", "requires", "stateModel", "parameters", "evidenceRequirements"],
  "categories": ["control", "motion", "interaction", "combat", "pressure", "goal", "economy", "progression", "lifecycle", "feedback", "space", "time"],
  "mechanics": {
    "control.directional": { "id": "control.directional", "revision": 1, "status": "approved-design", "category": "control", "semanticRefs": ["semantic-dictionary#/gameplayRoles/action_entry", "semantic-dictionary#/semantic_concepts/movement"], "provides": ["direction-intent"], "requires": ["controllable-actor"], "stateModel": ["idle", "active"], "parameters": ["axes", "inputPolicy"], "evidenceRequirements": ["input changes actor intent"] },
    "motion.platform": { "id": "motion.platform", "revision": 1, "status": "approved-design", "category": "motion", "semanticRefs": ["semantic-dictionary#/semantic_concepts/movement", "semantic-dictionary#/playIntents/jump-when-needed"], "provides": ["grounded-motion", "airborne-motion"], "requires": ["direction-intent", "ground-surface"], "stateModel": ["grounded", "rising", "falling"], "parameters": ["speed", "jumpProfile"], "evidenceRequirements": ["grounded and airborne transitions"] },
    "motion.top-down": { "id": "motion.top-down", "revision": 1, "status": "approved-design", "category": "motion", "semanticRefs": ["semantic-dictionary#/semantic_concepts/top_down_movement"], "provides": ["planar-motion"], "requires": ["direction-intent"], "stateModel": ["idle", "moving"], "parameters": ["speed", "acceleration"], "evidenceRequirements": ["independent world-axis movement"] },
    "interaction.contact": { "id": "interaction.contact", "revision": 1, "status": "approved-design", "category": "interaction", "semanticRefs": ["semantic-dictionary#/gameplayRoles/action_entry"], "provides": ["contact-event"], "requires": ["two-collidable-subjects"], "stateModel": ["separate", "contact"], "parameters": ["contactPolicy"], "evidenceRequirements": ["enter and leave contact evidence"] },
    "interaction.activate": { "id": "interaction.activate", "revision": 1, "status": "approved-design", "category": "interaction", "semanticRefs": ["semantic-dictionary#/gameplayRoles/action_entry"], "provides": ["activation-event"], "requires": ["actor", "interactable"], "stateModel": ["available", "activated", "cooldown"], "parameters": ["range", "repeatPolicy"], "evidenceRequirements": ["explicit actor activation"] },
    "combat.aim-fire": { "id": "combat.aim-fire", "revision": 1, "status": "approved-design", "category": "combat", "semanticRefs": ["semantic-dictionary#/semantic_concepts/aim_and_fire"], "provides": ["attack-intent", "projectile-or-hit"], "requires": ["actor", "target-policy"], "stateModel": ["ready", "attacking", "cooldown"], "parameters": ["targeting", "rate", "range"], "evidenceRequirements": ["attack produces targetable threat"] },
    "combat.damage-failure": { "id": "combat.damage-failure", "revision": 1, "status": "approved-design", "category": "combat", "semanticRefs": ["semantic-dictionary#/eventMeanings/ActorDamaged", "semantic-dictionary#/eventMeanings/ActorFailed"], "provides": ["damage", "failure-transition"], "requires": ["vital-state"], "stateModel": ["active", "damaged", "failed"], "parameters": ["maximumVital", "damagePolicy"], "evidenceRequirements": ["damage changes state and can cause failure"] },
    "pressure.chase": { "id": "pressure.chase", "revision": 1, "status": "approved-design", "category": "pressure", "semanticRefs": ["semantic-dictionary#/semantic_concepts/chase_pressure", "semantic-dictionary#/eventMeanings/PressureDetected"], "provides": ["spatial-pressure"], "requires": ["actor", "pressure-agent", "route"], "stateModel": ["searching", "pursuing", "resolved"], "parameters": ["speedRatio", "spawnPolicy"], "evidenceRequirements": ["pressure reduces safe space"] },
    "pressure.wave": { "id": "pressure.wave", "revision": 1, "status": "approved-design", "category": "pressure", "semanticRefs": ["semantic-dictionary#/gameplayRoles/pressure", "semantic-dictionary#/eventMeanings/PhaseTransitioned"], "provides": ["phased-pressure"], "requires": ["pressure-provider", "phase-driver"], "stateModel": ["preparing", "active", "recovery"], "parameters": ["densityCurve", "phaseDuration"], "evidenceRequirements": ["pressure changes across phases"] },
    "goal.collect": { "id": "goal.collect", "revision": 1, "status": "approved-design", "category": "goal", "semanticRefs": ["semantic-dictionary#/playGoals/collect", "semantic-dictionary#/eventMeanings/RewardReached"], "provides": ["collection-progress"], "requires": ["actor", "collectible"], "stateModel": ["available", "collected"], "parameters": ["targetCount", "respawnPolicy"], "evidenceRequirements": ["collection advances declared progress"] },
    "goal.survive": { "id": "goal.survive", "revision": 1, "status": "approved-design", "category": "goal", "semanticRefs": ["semantic-dictionary#/playGoals/survive", "semantic-dictionary#/playGoals/avoid-threats"], "provides": ["survival-progress"], "requires": ["pressure", "failure-transition"], "stateModel": ["surviving", "completed", "failed"], "parameters": ["duration", "completionPolicy"], "evidenceRequirements": ["sustained pressure and finite success"] },
    "goal.objective": { "id": "goal.objective", "revision": 1, "status": "approved-design", "category": "goal", "semanticRefs": ["semantic-dictionary#/playGoals/complete-objective"], "provides": ["objective-progress", "completion-event"], "requires": ["objective-state"], "stateModel": ["open", "completed", "failed"], "parameters": ["completionRule"], "evidenceRequirements": ["objective has measurable completion"] },
    "goal.solve-reset": { "id": "goal.solve-reset", "revision": 1, "status": "approved-design", "category": "goal", "semanticRefs": ["semantic-dictionary#/playGoals/solve", "semantic-dictionary#/eventMeanings/PuzzleReset"], "provides": ["solution-state", "reset-transition"], "requires": ["interaction-state", "constraints"], "stateModel": ["unsolved", "solved", "reset"], "parameters": ["solutionRule", "resetPolicy"], "evidenceRequirements": ["valid solution and recoverable invalid state"] },
    "economy.convert": { "id": "economy.convert", "revision": 1, "status": "approved-design", "category": "economy", "semanticRefs": ["semantic-dictionary#/semantic_concepts/resource_conversion"], "provides": ["resource-output"], "requires": ["resource-input"], "stateModel": ["available", "converting", "blocked"], "parameters": ["cost", "yield", "duration"], "evidenceRequirements": ["conservation and affordability"] },
    "progression.upgrade": { "id": "progression.upgrade", "revision": 1, "status": "approved-design", "category": "progression", "semanticRefs": ["semantic-dictionary#/playGoals/grow", "semantic-dictionary#/eventMeanings/UpgradeApplied"], "provides": ["persistent-improvement"], "requires": ["upgrade-choice", "progress-resource"], "stateModel": ["locked", "available", "applied"], "parameters": ["choices", "stackPolicy"], "evidenceRequirements": ["choice changes future play"] },
    "lifecycle.spawn-restart": { "id": "lifecycle.spawn-restart", "revision": 1, "status": "approved-design", "category": "lifecycle", "semanticRefs": ["semantic-dictionary#/eventMeanings/ActorSpawned", "semantic-dictionary#/eventMeanings/ActorFailed"], "provides": ["spawn", "restart"], "requires": ["actor-prototype"], "stateModel": ["absent", "active", "failed"], "parameters": ["spawnPolicy", "restartPolicy"], "evidenceRequirements": ["failure can return to playable state"] },
    "feedback.state": { "id": "feedback.state", "revision": 1, "status": "approved-design", "category": "feedback", "semanticRefs": ["semantic-dictionary#/gameplayRoles/feedback"], "provides": ["state-feedback"], "requires": ["observable-state"], "stateModel": ["hidden", "visible"], "parameters": ["channels", "priority"], "evidenceRequirements": ["critical state is player-visible"] },
    "space.route": { "id": "space.route", "revision": 1, "status": "approved-design", "category": "space", "semanticRefs": ["semantic-dictionary#/gameplayRoles/route"], "provides": ["traversable-route"], "requires": ["regions"], "stateModel": ["open", "blocked", "completed"], "parameters": ["topology", "branching"], "evidenceRequirements": ["start-to-goal connectivity"] },
    "time.phase": { "id": "time.phase", "revision": 1, "status": "approved-design", "category": "time", "semanticRefs": ["semantic-dictionary#/gameplayRoles/phase_driver", "semantic-dictionary#/eventMeanings/PhaseTransitioned"], "provides": ["phase-clock"], "requires": ["phase-definition"], "stateModel": ["running", "transitioning", "complete"], "parameters": ["duration", "transitionPolicy"], "evidenceRequirements": ["ordered measurable phase transitions"] }
  },
  "approvedRevisions": {
    "control.directional": { "1": { "mechanicId": "control.directional", "revision": 1, "contentHash": "5ab61b4e1114fca1878430f7f058cb46e408245778e3f031c77e28c0e3907104", "sourceMechanicId": "control.directional", "status": "approved" } },
    "motion.platform": { "1": { "mechanicId": "motion.platform", "revision": 1, "contentHash": "9eac95e61df5602692a595ecebd7da2b934b41b1e1976a4ad8f1d5eb1ecc7f92", "sourceMechanicId": "motion.platform", "status": "approved" } },
    "motion.top-down": { "1": { "mechanicId": "motion.top-down", "revision": 1, "contentHash": "ba44f0b59fcd242a205066d116747fdcec7b62924899f8e540a1c714f80814c2", "sourceMechanicId": "motion.top-down", "status": "approved" } },
    "interaction.activate": { "1": { "mechanicId": "interaction.activate", "revision": 1, "contentHash": "1fb1968401165687e8cd12c763f4f989a7c98a483b1811e3a705f6ce785f69ec", "sourceMechanicId": "interaction.activate", "status": "approved" } },
    "combat.aim-fire": { "1": { "mechanicId": "combat.aim-fire", "revision": 1, "contentHash": "e1a429e317639bb2f0b085d1e36b6b0bddcdbf7b51f1b8f06a1ebca4078a2933", "sourceMechanicId": "combat.aim-fire", "status": "approved" } },
    "combat.damage-failure": { "1": { "mechanicId": "combat.damage-failure", "revision": 1, "contentHash": "969a3e394a1803867a83295c427b8f321d0361bef8e03b8f1c08bd5b7344039d", "sourceMechanicId": "combat.damage-failure", "status": "approved" } },
    "pressure.chase": { "1": { "mechanicId": "pressure.chase", "revision": 1, "contentHash": "37e8b7c7e916fa8f61c99e6f609735a94b95ee957561c1d5b66736b74f897db7", "sourceMechanicId": "pressure.chase", "status": "approved" } },
    "pressure.wave": { "1": { "mechanicId": "pressure.wave", "revision": 1, "contentHash": "ba6f7082a139fda69e16d8a26a2201afe6111b22e20b2c9c84e377a419e95cd8", "sourceMechanicId": "pressure.wave", "status": "approved" } },
    "goal.collect": { "1": { "mechanicId": "goal.collect", "revision": 1, "contentHash": "51407d82960d50e5938a55606c93e0fece1876db078fa4a2f80638b800d1429e", "sourceMechanicId": "goal.collect", "status": "approved" } },
    "goal.survive": { "1": { "mechanicId": "goal.survive", "revision": 1, "contentHash": "3142725b28c378a6cf30609362c19e38a95f7aaa974261eec2a6cb52a0c1bbee", "sourceMechanicId": "goal.survive", "status": "approved" } },
    "goal.objective": { "1": { "mechanicId": "goal.objective", "revision": 1, "contentHash": "ca4414a9c7de099ca9ab5cdd805dd91e9b6c9c4ef5f5543fa1c242185dba0ecc", "sourceMechanicId": "goal.objective", "status": "approved" } },
    "goal.solve-reset": { "1": { "mechanicId": "goal.solve-reset", "revision": 1, "contentHash": "3562f88c1e4a4fbaf8ecb28d13b4c8d0fcd7999d6f0289d6c7ae3ab985eb2075", "sourceMechanicId": "goal.solve-reset", "status": "approved" } },
    "economy.convert": { "1": { "mechanicId": "economy.convert", "revision": 1, "contentHash": "2a10445cce53ea0dd76ef57b3d1e35265042899e923499b100c914a7c61c7c1d", "sourceMechanicId": "economy.convert", "status": "approved" } },
    "progression.upgrade": { "1": { "mechanicId": "progression.upgrade", "revision": 1, "contentHash": "2c9a06d4c1c6709243715bc1c6097b555c54e3046289b4d470aacdb3c20849b5", "sourceMechanicId": "progression.upgrade", "status": "approved" } },
    "lifecycle.spawn-restart": { "1": { "mechanicId": "lifecycle.spawn-restart", "revision": 1, "contentHash": "bdc8d1235d80de86fd38a4163a4c10a8adf28425d3795d7cf842bf6a2c74321c", "sourceMechanicId": "lifecycle.spawn-restart", "status": "approved" } },
    "feedback.state": { "1": { "mechanicId": "feedback.state", "revision": 1, "contentHash": "d99fd0aaf15880cde5712710952f581051d839fe2b5e5de32225f1d18bd24ad6", "sourceMechanicId": "feedback.state", "status": "approved" } },
    "space.route": { "1": { "mechanicId": "space.route", "revision": 1, "contentHash": "caa98d691f35709b5ee6ac4b165d94b7ee4965739a92b513c2e604a8a2e50abf", "sourceMechanicId": "space.route", "status": "approved" } },
    "time.phase": { "1": { "mechanicId": "time.phase", "revision": 1, "contentHash": "2f20c8961006e53babacfa3f425780225f9347c879ec2d98db1a95c36929bcd0", "sourceMechanicId": "time.phase", "status": "approved" } }
  },
  "resolutionRules": [
    "Blueprint capability slots and module provides/requires use only executable mechanic refs pinned to mechanicId, revision, and contentHash.",
    "Discovery mechanic entries cannot participate in online composition until promoted into approvedRevisions.",
    "Bare mechanic labels are invalid machine input.",
    "A mechanic entry cannot redefine semantic meaning or GDJS instruction signatures.",
    "New mechanics are added by immutable revision and cross-reference closure checks, never by Planner switch branches."
  ]
}
